linkvertise/__init__.py
linkvertise/client.py
linkvertise-1.1.5.dist-info/METADATA
linkvertise-1.1.5.dist-info/WHEEL
linkvertise-1.1.5.dist-info/top_level.txt
linkvertise-1.1.5.dist-info/RECORD
