Metadata-Version: 2.1
Name: linkvertise
Version: 1.1.5
Summary: Python wrapper for linkvertise monetizing api.
Home-page: https://github.com/Nohet/linkvertise.py
Author: Nohet
Author-email: igorczupryniak503@gmail.com
License: MIT
Keywords: linkvertise,linkvertise wrapper,linkvertise api,linkvertise monetizing
Platform: UNKNOWN
Classifier: Development Status :: 3 - Alpha
Classifier: Intended Audience :: Developers
Classifier: License :: OSI Approved :: MIT License
Classifier: Programming Language :: Python :: 3
